README.txt
setup.py
ROC/Analyze.py
ROC/DataOfRoc.py
ROC/IOU.py
ROC/__init__.py
ROC/drawpic.py
ROC/read.py
ROC/roc.py
ROC/scoreRoc.py
nms/__init__.py
roc2.1.5.egg-info/PKG-INFO
roc2.1.5.egg-info/SOURCES.txt
roc2.1.5.egg-info/dependency_links.txt
roc2.1.5.egg-info/top_level.txt
transform/__init__.py
transform/txt2xml.py
transform/xml2txt.py